crypt_keeper
