Metadata-Version: 1.0
Name: crypt-keeper
Version: 0.0.5
Summary: Secure password keeper and generator.
Home-page: https://github.com/wybiral/crypt_keeper/
Author: Davy Wybiral
Author-email: davy.wybiral@gmail.com
License: UNKNOWN
Platform: any
